kitti360scripts/__init__.py
kitti360scripts/devkits/__init__.py
kitti360scripts/devkits/commons/__init__.py
kitti360scripts/devkits/commons/loadCalibration.py
kitti360scripts/evaluation/__init__.py
kitti360scripts/evaluation/semantic_2d/__init__.py
kitti360scripts/evaluation/semantic_2d/evalInstanceLevelSemanticLabeling.py
kitti360scripts/evaluation/semantic_2d/evalPixelLevelSemanticLabeling.py
kitti360scripts/evaluation/semantic_2d/instance.py
kitti360scripts/evaluation/semantic_2d/instances2dict.py
kitti360scripts/helpers/__init__.py
kitti360scripts/helpers/annotation.py
kitti360scripts/helpers/csHelpers.py
kitti360scripts/helpers/data.py
kitti360scripts/helpers/labels.py
kitti360scripts/helpers/ply.py
kitti360scripts/helpers/pointcloud.py
kitti360scripts/helpers/project.py
kitti360scripts/viewer/__init__.py
kitti360scripts/viewer/kitti360Viewer.py
kitti360scripts/viewer/kitti360Viewer3D.py
kitti360scripts/viewer/kitti360Viewer3DRaw.py
kitti360scripts/viewer/icons/back.png
kitti360scripts/viewer/icons/disp.png
kitti360scripts/viewer/icons/exit.png
kitti360scripts/viewer/icons/filepath.png
kitti360scripts/viewer/icons/help19.png
kitti360scripts/viewer/icons/minus.png
kitti360scripts/viewer/icons/next.png
kitti360scripts/viewer/icons/open.png
kitti360scripts/viewer/icons/play.png
kitti360scripts/viewer/icons/plus.png
kitti360scripts/viewer/icons/shuffle.png
kitti360scripts/viewer/icons/switch.png
kitti360scripts/viewer/icons/zoom.png
kitti360Scripts-1.0.0.dist-info/LICENSE
kitti360Scripts-1.0.0.dist-info/METADATA
kitti360Scripts-1.0.0.dist-info/WHEEL
kitti360Scripts-1.0.0.dist-info/entry_points.txt
kitti360Scripts-1.0.0.dist-info/top_level.txt
kitti360Scripts-1.0.0.dist-info/RECORD
