Metadata-Version: 2.1
Name: kitti360Scripts
Version: 1.0.0
Summary: Scripts for the KITTI-360 Dataset
Home-page: https://github.com/autonomousvision/kitti360Scripts
Author: Yiyi Liao
License: https://github.com/autonomousvision/kitti360Scripts/blob/master/license.txt
License-File: LICENSE
Requires-Dist: numpy
Requires-Dist: matplotlib
Requires-Dist: pillow
Requires-Dist: pyyaml
Requires-Dist: scikit-image
